avg_cal/__init__.py
avg_cal/avg.py
avg_cal/first/__init__.py
avg_cal/first/div.py
avg_cal/first/vote_eligibility_check.py
avg_cal/second/__init__.py
avg_cal/second/addition.py
avg_cal/second/mul.py
avg_cal/second/sub.py
avg_cal-0.1.dist-info/LICENCE.txt
avg_cal-0.1.dist-info/METADATA
avg_cal-0.1.dist-info/WHEEL
avg_cal-0.1.dist-info/top_level.txt
avg_cal-0.1.dist-info/RECORD
