Metadata-Version: 2.1
Name: avg-cal
Version: 0.1
Summary: here you find bmi,math problem solution
Home-page: UNKNOWN
Author: sumathi123
Author-email: sumathi.krishnasamy@hexacorp.com
License: UNKNOWN
Platform: UNKNOWN
Classifier: Programming Language :: Python :: 3
Classifier: License :: OSI Approved :: MIT License
Classifier: Operating System :: OS Independent
License-File: LICENCE.txt
